qutip/__init__.py
qutip/_distributions.cp312-win_amd64.pyd
qutip/_distributions.cpp
qutip/_distributions.pyx
qutip/about.py
qutip/animation.py
qutip/bloch.py
qutip/cite.py
qutip/continuous_variables.py
qutip/control.py
qutip/distributions.py
qutip/entropy.py
qutip/fileio.py
qutip/ipynbtools.py
qutip/matplotlib_utilities.py
qutip/measurement.py
qutip/partial_transpose.py
qutip/qip.py
qutip/random_objects.py
qutip/settings.py
qutip/simdiag.py
qutip/testing.py
qutip/tomography.py
qutip/typing.py
qutip/utilities.py
qutip/version.py
qutip/visualization.py
qutip/wigner.py
qutip/_mkl/__init__.py
qutip/_mkl/spmv.py
qutip/_mkl/spsolve.py
qutip/core/__init__.py
qutip/core/_brtensor.cp312-win_amd64.pyd
qutip/core/_brtensor.cpp
qutip/core/_brtensor.pyx
qutip/core/_brtools.cp312-win_amd64.pyd
qutip/core/_brtools.cpp
qutip/core/_brtools.pxd
qutip/core/_brtools.pyx
qutip/core/blochredfield.py
qutip/core/coefficient.py
qutip/core/dimensions.py
qutip/core/energy_restricted.py
qutip/core/environment.py
qutip/core/expect.py
qutip/core/gates.py
qutip/core/metrics.py
qutip/core/numpy_backend.py
qutip/core/operators.py
qutip/core/options.py
qutip/core/properties.py
qutip/core/qobj.py
qutip/core/semidefinite.py
qutip/core/states.py
qutip/core/subsystem_apply.py
qutip/core/superop_reps.py
qutip/core/superoperator.py
qutip/core/tensor.py
qutip/core/cy/__init__.py
qutip/core/cy/_element.cp312-win_amd64.pyd
qutip/core/cy/_element.cpp
qutip/core/cy/_element.pxd
qutip/core/cy/_element.pyx
qutip/core/cy/coefficient.cp312-win_amd64.pyd
qutip/core/cy/coefficient.cpp
qutip/core/cy/coefficient.pxd
qutip/core/cy/coefficient.pyx
qutip/core/cy/complex_math.pxd
qutip/core/cy/math.cp312-win_amd64.pyd
qutip/core/cy/math.cpp
qutip/core/cy/math.pxd
qutip/core/cy/math.pyx
qutip/core/cy/qobjevo.cp312-win_amd64.pyd
qutip/core/cy/qobjevo.cpp
qutip/core/cy/qobjevo.pxd
qutip/core/cy/qobjevo.pyi
qutip/core/cy/qobjevo.pyx
qutip/core/cy/openmp/__init__.py
qutip/core/cy/openmp/bench_openmp.py
qutip-5.2.3.dist-info/licenses/LICENSE.txt
qutip-5.2.3.dist-info/METADATA
qutip-5.2.3.dist-info/WHEEL
qutip-5.2.3.dist-info/top_level.txt
qutip-5.2.3.dist-info/RECORD
