Metadata-Version: 2.4
Name: qutip
Version: 5.2.3
Summary: QuTiP: The Quantum Toolbox in Python
Author: Alexander Pitchford, Paul D. Nation, Robert J. Johansson, Chris Granade, Arne Grimsmo, Nathan Shammah, Shahnawaz Ahmed, Neill Lambert, Eric Giguère, Boxi Li, Jake Lishman, Simon Cross
Author-email: qutip-admin@googlegroups.com
License-Expression: BSD-3-Clause
Project-URL: Homepage, https://qutip.org
Project-URL: Issues, https://github.com/qutip/qutip/issues
Project-URL: Documentation, https://qutip.readthedocs.io/en/stable/
Project-URL: Source Code, https://github.com/qutip/qutip
Keywords: quantum,physics,dynamics
Classifier: Development Status :: 2 - Pre-Alpha
Classifier: Intended Audience :: Science/Research
Classifier: Programming Language :: Python
Classifier: Programming Language :: Python :: 3
Classifier: Topic :: Scientific/Engineering
Classifier: Operating System :: MacOS
Classifier: Operating System :: POSIX
Classifier: Operating System :: Unix
Classifier: Operating System :: Microsoft :: Windows
Requires-Python: >=3.10
License-File: LICENSE.txt
Requires-Dist: numpy>=1.22
Requires-Dist: scipy!=1.16.0,!=1.17.0,>=1.9
Requires-Dist: packaging
Provides-Extra: graphics
Requires-Dist: matplotlib>=3.5; extra == "graphics"
Provides-Extra: runtime-compilation
Requires-Dist: cython>=0.29.20; extra == "runtime-compilation"
Requires-Dist: filelock; extra == "runtime-compilation"
Requires-Dist: setuptools; extra == "runtime-compilation"
Provides-Extra: semidefinite
Requires-Dist: cvxpy>=1.0; extra == "semidefinite"
Requires-Dist: cvxopt; extra == "semidefinite"
Provides-Extra: tests
Requires-Dist: pytest>=5.2; extra == "tests"
Requires-Dist: pytest-rerunfailures; extra == "tests"
Provides-Extra: ipython
Requires-Dist: ipython; extra == "ipython"
Provides-Extra: extras
Requires-Dist: loky; python_version >= "3.11" and extra == "extras"
Requires-Dist: loky!=3.5.0; python_version <= "3.10" and extra == "extras"
Requires-Dist: tqdm; extra == "extras"
Requires-Dist: mpmath; extra == "extras"
Provides-Extra: mpi
Requires-Dist: mpi4py; extra == "mpi"
Provides-Extra: full
Requires-Dist: qutip[extras,graphics,ipython,runtime_compilation,semidefinite,tests]; extra == "full"
Dynamic: license-file
